{"title": "Identity and culture", "lang": "es", "youtube": null, "phrases": [{"tokens_html": "<a style=\"color:#fd7e14;text-decoration:none\" href=\"#\" class=\"word\" data-name=\"hola\" data-lang=\"es\">Hola</a><a style=\"color:#a71d5d;text-decoration:none\" href=\"#\" class=\"word\" data-name=\",\" data-lang=\"es\">,</a><a style=\"color:#a71d5d;text-decoration:none\" href=\"#\" class=\"word\" data-name=\"¿\" data-lang=\"es\">¿</a><a style=\"color:#fd7e14;text-decoration:none\" href=\"#\" class=\"word\" data-name=\"cómo\" data-lang=\"es\">cómo</a><a style=\"color:#fd7e14;text-decoration:none\" href=\"#\" class=\"word\" data-name=\"estás\" data-lang=\"es\">estás</a><a style=\"color:#a71d5d;text-decoration:none\" href=\"#\" class=\"word\" data-name=\"?\" data-lang=\"es\">?</a>", "translation": "Hello how are you ?", "audio": null}, {"tokens_html": "<a style=\"color:#fd7e14;text-decoration:none\" href=\"#\" class=\"word\" data-name=\"bien\" data-lang=\"es\">Bien</a><a style=\"color:#a71d5d;text-decoration:none\" href=\"#\" class=\"word\" data-name=\",\" data-lang=\"es\">,</a><a style=\"color:#a71d5d;text-decoration:none\" href=\"#\" class=\"word\" data-name=\"¿\" data-lang=\"es\">¿</a><a style=\"color:#fd7e14;text-decoration:none\" href=\"#\" class=\"word\" data-name=\"y\" data-lang=\"es\">y</a><a style=\"color:#fd7e14;text-decoration:none\" href=\"#\" class=\"word\" data-name=\"tú\" data-lang=\"es\">tú</a><a style=\"color:#a71d5d;text-decoration:none\" href=\"#\" class=\"word\" data-name=\"?\" data-lang=\"es\">?</a>", "translation": "Good and you ?", "audio": null}, {"tokens_html": "<a style=\"color:#fd7e14;text-decoration:none\" href=\"#\" class=\"word\" data-name=\"bien\" data-lang=\"es\">Bien</a><a style=\"color:#a71d5d;text-decoration:none\" href=\"#\" class=\"word\" data-name=\",\" data-lang=\"es\">,</a><a style=\"color:#fd7e14;text-decoration:none\" href=\"#\" class=\"word\" data-name=\"gracias\" data-lang=\"es\">gracias</a><a style=\"color:#a71d5d;text-decoration:none\" href=\"#\" class=\"word\" data-name=\".\" data-lang=\"es\">.</a><a style=\"color:#a71d5d;text-decoration:none\" href=\"#\" class=\"word\" data-name=\"¿\" data-lang=\"es\">¿</a><a style=\"color:#a71d5d;text-decoration:none\" href=\"#\" class=\"word\" data-name=\"usas\" data-lang=\"es\">Usas</a><a style=\"color:#a71d5d;text-decoration:none\" href=\"#\" class=\"word\" data-name=\"móvil\" data-lang=\"es\">móvil</a><a style=\"color:#a71d5d;text-decoration:none\" href=\"#\" class=\"word\" data-name=\"?\" data-lang=\"es\">?</a>", "translation": "Fine, thanks . Do you use mobile?", "audio": null}, {"tokens_html": "<a style=\"color:#fd7e14;text-decoration:none\" href=\"#\" class=\"word\" data-name=\"sí\" data-lang=\"es\">Sí</a><a style=\"color:#a71d5d;text-decoration:none\" href=\"#\" class=\"word\" data-name=\",\" data-lang=\"es\">,</a><a style=\"color:#fd7e14;text-decoration:none\" href=\"#\" class=\"word\" data-name=\"y\" data-lang=\"es\">y</a><a style=\"color:#fd7e14;text-decoration:none\" href=\"#\" class=\"word\" data-name=\"mi\" data-lang=\"es\">mi</a><a style=\"color:#fd7e14;text-decoration:none\" href=\"#\" class=\"word\" data-name=\"familia\" data-lang=\"es\">familia</a><a style=\"color:#fd7e14;text-decoration:none\" href=\"#\" class=\"word\" data-name=\"también\" data-lang=\"es\">también</a><a style=\"color:#a71d5d;text-decoration:none\" href=\"#\" class=\"word\" data-name=\".\" data-lang=\"es\">.</a>", "translation": "Yes , and my family too .", "audio": null}, {"tokens_html": "<a style=\"color:#fd7e14;text-decoration:none\" href=\"#\" class=\"word\" data-name=\"mi\" data-lang=\"es\">Mi</a><a style=\"color:#fd7e14;text-decoration:none\" href=\"#\" class=\"word\" data-name=\"mamá\" data-lang=\"es\">mamá</a><a style=\"color:#a71d5d;text-decoration:none\" href=\"#\" class=\"word\" data-name=\"usa\" data-lang=\"es\">usa</a><a style=\"color:#a71d5d;text-decoration:none\" href=\"#\" class=\"word\" data-name=\"apps\" data-lang=\"es\">apps</a><a style=\"color:#fd7e14;text-decoration:none\" href=\"#\" class=\"word\" data-name=\"para\" data-lang=\"es\">para</a><a style=\"color:#fd7e14;text-decoration:none\" href=\"#\" class=\"word\" data-name=\"comprar\" data-lang=\"es\">comprar</a><a style=\"color:#a71d5d;text-decoration:none\" href=\"#\" class=\"word\" data-name=\".\" data-lang=\"es\">.</a>", "translation": "My mom uses apps to shop.", "audio": null}, {"tokens_html": "<a style=\"color:#fd7e14;text-decoration:none\" href=\"#\" class=\"word\" data-name=\"mi\" data-lang=\"es\">Mi</a><a style=\"color:#fd7e14;text-decoration:none\" href=\"#\" class=\"word\" data-name=\"papá\" data-lang=\"es\">papá</a><a style=\"color:#a71d5d;text-decoration:none\" href=\"#\" class=\"word\" data-name=\"usa\" data-lang=\"es\">usa</a><a style=\"color:#a71d5d;text-decoration:none\" href=\"#\" class=\"word\" data-name=\"gps\" data-lang=\"es\">GPS</a><a style=\"color:#a71d5d;text-decoration:none\" href=\"#\" class=\"word\" data-name=\".\" data-lang=\"es\">.</a>", "translation": "My dad uses GPS.", "audio": null}, {"tokens_html": "<a style=\"color:#fd7e14;text-decoration:none\" href=\"#\" class=\"word\" data-name=\"mi\" data-lang=\"es\">Mi</a><a style=\"color:#fd7e14;text-decoration:none\" href=\"#\" class=\"word\" data-name=\"hermana\" data-lang=\"es\">hermana</a><a style=\"color:#a71d5d;text-decoration:none\" href=\"#\" class=\"word\" data-name=\"ama\" data-lang=\"es\">ama</a><a style=\"color:#fd7e14;text-decoration:none\" href=\"#\" class=\"word\" data-name=\"su\" data-lang=\"es\">su</a><a style=\"color:#a71d5d;text-decoration:none\" href=\"#\" class=\"word\" data-name=\"tablet\" data-lang=\"es\">tablet</a><a style=\"color:#a71d5d;text-decoration:none\" href=\"#\" class=\"word\" data-name=\".\" data-lang=\"es\">.</a>", "translation": "My sister loves her tablet.", "audio": null}, {"tokens_html": "<a style=\"color:#fd7e14;text-decoration:none\" href=\"#\" class=\"word\" data-name=\"es\" data-lang=\"es\">Es</a><a style=\"color:#fd7e14;text-decoration:none\" href=\"#\" class=\"word\" data-name=\"verdad\" data-lang=\"es\">verdad</a><a style=\"color:#a71d5d;text-decoration:none\" href=\"#\" class=\"word\" data-name=\",\" data-lang=\"es\">,</a><a style=\"color:#fd7e14;text-decoration:none\" href=\"#\" class=\"word\" data-name=\"la\" data-lang=\"es\">la</a><a style=\"color:#a71d5d;text-decoration:none\" href=\"#\" class=\"word\" data-name=\"tecnología\" data-lang=\"es\">tecnología</a><a style=\"color:#fd7e14;text-decoration:none\" href=\"#\" class=\"word\" data-name=\"es\" data-lang=\"es\">es</a><a style=\"color:#a71d5d;text-decoration:none\" href=\"#\" class=\"word\" data-name=\"útil\" data-lang=\"es\">útil</a><a style=\"color:#a71d5d;text-decoration:none\" href=\"#\" class=\"word\" data-name=\".\" data-lang=\"es\">.</a>", "translation": "It &#x27;s true , technology is useful .", "audio": null}, {"tokens_html": "<a style=\"color:#fd7e14;text-decoration:none\" href=\"#\" class=\"word\" data-name=\"sí\" data-lang=\"es\">Sí</a><a style=\"color:#a71d5d;text-decoration:none\" href=\"#\" class=\"word\" data-name=\",\" data-lang=\"es\">,</a><a style=\"color:#fd7e14;text-decoration:none\" href=\"#\" class=\"word\" data-name=\"pero\" data-lang=\"es\">pero</a><a style=\"color:#fd7e14;text-decoration:none\" href=\"#\" class=\"word\" data-name=\"también\" data-lang=\"es\">también</a><a style=\"color:#fd7e14;text-decoration:none\" href=\"#\" class=\"word\" data-name=\"me\" data-lang=\"es\">me</a><a style=\"color:#fd7e14;text-decoration:none\" href=\"#\" class=\"word\" data-name=\"gusta\" data-lang=\"es\">gusta</a><a style=\"color:#fd7e14;text-decoration:none\" href=\"#\" class=\"word\" data-name=\"hablar\" data-lang=\"es\">hablar</a><a style=\"color:#fd7e14;text-decoration:none\" href=\"#\" class=\"word\" data-name=\"en\" data-lang=\"es\">en</a><a style=\"color:#fd7e14;text-decoration:none\" href=\"#\" class=\"word\" data-name=\"persona\" data-lang=\"es\">persona</a><a style=\"color:#a71d5d;text-decoration:none\" href=\"#\" class=\"word\" data-name=\".\" data-lang=\"es\">.</a>", "translation": "Yes , but I also like to talk in person .", "audio": null}], "wordData": {"es|tú": {"definition": "your", "rank": 46, "audio": "https://storage.googleapis.com/createflashcardapp.appspot.com/common/audio/es/word_t%C3%BA.mp3", "href": "word.html?lang=es&w=t%C3%BA", "inTop": true}, "es|cómo": {"definition": "What", "rank": 54, "audio": "https://storage.googleapis.com/createflashcardapp.appspot.com/common/audio/es/word_c%C3%B3mo.mp3", "href": "word.html?lang=es&w=c%C3%B3mo", "inTop": true}, "es|papá": {"definition": "father", "rank": 156, "audio": "https://storage.googleapis.com/createflashcardapp.appspot.com/common/audio/es/word_pap%C3%A1.mp3", "href": "word.html?lang=es&w=pap%C3%A1", "inTop": true}, "es|gps": {"rank": 9255, "audio": "https://storage.googleapis.com/createflashcardapp.appspot.com/common/audio/es/word_gps.mp3", "href": "word.html?lang=es&w=gps", "inTop": false}, "es|persona": {"definition": "person", "rank": 330, "audio": "https://storage.googleapis.com/createflashcardapp.appspot.com/common/audio/es/word_persona.mp3", "href": "word.html?lang=es&w=persona", "inTop": true}, "es|móvil": {"definition": "mobile", "rank": 4158, "audio": "https://storage.googleapis.com/createflashcardapp.appspot.com/common/audio/es/word_m%C3%B3vil.mp3", "href": "word.html?lang=es&w=m%C3%B3vil", "inTop": false}, "es|bien": {"definition": "right", "rank": 23, "audio": "https://storage.googleapis.com/createflashcardapp.appspot.com/common/audio/es/word_bien.mp3", "href": "word.html?lang=es&w=bien", "inTop": true}, "es|usa": {"definition": "uses", "rank": 1133, "audio": "https://storage.googleapis.com/createflashcardapp.appspot.com/common/audio/es/word_usa.mp3", "href": "word.html?lang=es&w=usa", "inTop": false}, "es|me": {"definition": "I", "rank": 14, "audio": "https://storage.googleapis.com/createflashcardapp.appspot.com/common/audio/es/word_me.mp3", "href": "word.html?lang=es&w=me", "inTop": true}, "es|mamá": {"definition": "breast", "rank": 149, "audio": "https://storage.googleapis.com/createflashcardapp.appspot.com/common/audio/es/word_mam%C3%A1.mp3", "href": "word.html?lang=es&w=mam%C3%A1", "inTop": true}, "es|tecnología": {"definition": "technology", "rank": 1801, "audio": "https://storage.googleapis.com/createflashcardapp.appspot.com/common/audio/es/word_tecnolog%C3%ADa.mp3", "href": "word.html?lang=es&w=tecnolog%C3%ADa", "inTop": false}, "es|mi": {"definition": "me", "rank": 24, "audio": "https://storage.googleapis.com/createflashcardapp.appspot.com/common/audio/es/word_mi.mp3", "href": "word.html?lang=es&w=mi", "inTop": true}, "es|es": {"definition": "it is", "rank": 7, "audio": "https://storage.googleapis.com/createflashcardapp.appspot.com/common/audio/es/word_es.mp3", "href": "word.html?lang=es&w=es", "inTop": true}, "es|y": {"definition": "and", "rank": 8, "audio": "https://storage.googleapis.com/createflashcardapp.appspot.com/common/audio/es/word_y.mp3", "href": "word.html?lang=es&w=y", "inTop": true}, "es|,": {"audio": "https://storage.googleapis.com/createflashcardapp.appspot.com/common/audio/es/word_%2C.mp3", "href": "word.html?lang=es&w=%2C", "inTop": false}, "es|comprar": {"definition": "to buy", "rank": 806, "audio": "https://storage.googleapis.com/createflashcardapp.appspot.com/common/audio/es/word_comprar.mp3", "href": "word.html?lang=es&w=comprar", "inTop": true}, "es|ama": {"definition": "loves", "rank": 1284, "audio": "https://storage.googleapis.com/createflashcardapp.appspot.com/common/audio/es/word_ama.mp3", "href": "word.html?lang=es&w=ama", "inTop": false}, "es|apps": {"audio": "https://storage.googleapis.com/createflashcardapp.appspot.com/common/audio/es/word_apps.mp3", "href": "word.html?lang=es&w=apps", "inTop": false}, "es|tablet": {"audio": "https://storage.googleapis.com/createflashcardapp.appspot.com/common/audio/es/word_tablet.mp3", "href": "word.html?lang=es&w=tablet", "inTop": false}, "es|útil": {"definition": "Useful", "rank": 2426, "audio": "https://storage.googleapis.com/createflashcardapp.appspot.com/common/audio/es/word_%C3%BAtil.mp3", "href": "word.html?lang=es&w=%C3%BAtil", "inTop": false}, "es|para": {"definition": "for", "rank": 21, "audio": "https://storage.googleapis.com/createflashcardapp.appspot.com/common/audio/es/word_para.mp3", "href": "word.html?lang=es&w=para", "inTop": true}, "es|pero": {"definition": "but", "rank": 25, "audio": "https://storage.googleapis.com/createflashcardapp.appspot.com/common/audio/es/word_pero.mp3", "href": "word.html?lang=es&w=pero", "inTop": true}, "es|gusta": {"definition": "like", "rank": 193, "audio": "https://storage.googleapis.com/createflashcardapp.appspot.com/common/audio/es/word_gusta.mp3", "href": "word.html?lang=es&w=gusta", "inTop": true}, "es|hola": {"definition": "hello", "rank": 64, "audio": "https://storage.googleapis.com/createflashcardapp.appspot.com/common/audio/es/word_hola.mp3", "href": "word.html?lang=es&w=hola", "inTop": true}, "es|.": {"definition": ".", "audio": "https://storage.googleapis.com/createflashcardapp.appspot.com/common/audio/es/word_..mp3", "href": "word.html?lang=es&w=.", "inTop": false}, "es|verdad": {"definition": "TRUE", "rank": 93, "audio": "https://storage.googleapis.com/createflashcardapp.appspot.com/common/audio/es/word_verdad.mp3", "href": "word.html?lang=es&w=verdad", "inTop": true}, "es|familia": {"definition": "family", "rank": 250, "audio": "https://storage.googleapis.com/createflashcardapp.appspot.com/common/audio/es/word_familia.mp3", "href": "word.html?lang=es&w=familia", "inTop": true}, "es|también": {"definition": "also", "rank": 115, "audio": "https://storage.googleapis.com/createflashcardapp.appspot.com/common/audio/es/word_tambi%C3%A9n.mp3", "href": "word.html?lang=es&w=tambi%C3%A9n", "inTop": true}, "es|sí": {"definition": "Yes", "rank": 20, "audio": "https://storage.googleapis.com/createflashcardapp.appspot.com/common/audio/es/word_s%C3%AD.mp3", "href": "word.html?lang=es&w=s%C3%AD", "inTop": true}, "es|estás": {"definition": "are", "rank": 47, "audio": "https://storage.googleapis.com/createflashcardapp.appspot.com/common/audio/es/word_est%C3%A1s.mp3", "href": "word.html?lang=es&w=est%C3%A1s", "inTop": true}, "es|en": {"definition": "in", "rank": 9, "audio": "https://storage.googleapis.com/createflashcardapp.appspot.com/common/audio/es/word_en.mp3", "href": "word.html?lang=es&w=en", "inTop": true}, "es|su": {"definition": "its", "rank": 30, "audio": "https://storage.googleapis.com/createflashcardapp.appspot.com/common/audio/es/word_su.mp3", "href": "word.html?lang=es&w=su", "inTop": true}, "es|?": {"audio": "https://storage.googleapis.com/createflashcardapp.appspot.com/common/audio/es/word_%3F.mp3", "href": "word.html?lang=es&w=%3F", "inTop": false}, "es|hablar": {"definition": "speak", "rank": 146, "audio": "https://storage.googleapis.com/createflashcardapp.appspot.com/common/audio/es/word_hablar.mp3", "href": "word.html?lang=es&w=hablar", "inTop": true}, "es|hermana": {"definition": "sister", "rank": 476, "audio": "https://storage.googleapis.com/createflashcardapp.appspot.com/common/audio/es/word_hermana.mp3", "href": "word.html?lang=es&w=hermana", "inTop": true}, "es|usas": {"rank": 3083, "audio": "https://storage.googleapis.com/createflashcardapp.appspot.com/common/audio/es/word_usas.mp3", "href": "word.html?lang=es&w=usas", "inTop": false}, "es|¿": {"audio": "https://storage.googleapis.com/createflashcardapp.appspot.com/common/audio/es/word_%C2%BF.mp3", "href": "word.html?lang=es&w=%C2%BF", "inTop": false}, "es|la": {"definition": "the", "rank": 5, "audio": "https://storage.googleapis.com/createflashcardapp.appspot.com/common/audio/es/word_la.mp3", "href": "word.html?lang=es&w=la", "inTop": true}, "es|gracias": {"definition": "Thank you", "rank": 63, "audio": "https://storage.googleapis.com/createflashcardapp.appspot.com/common/audio/es/word_gracias.mp3", "href": "word.html?lang=es&w=gracias", "inTop": true}}}